[
    {
        "key": "dbln",
        "value": "%7B%2261573774132103%22%3A%22CYyeH8cn%22%7D",
        "domain": "facebook.com",
        "path": "/login/device-based/",
        "hostOnly": false,
        "creation": "2025-07-03T09:12:54.622Z",
        "lastAccessed": "2025-07-03T09:12:54.623Z"
    },
    {
        "key": "datr",
        "value": "wTdUaA1LZmU_MLMpgWImj8qu",
        "domain": "facebook.com",
        "path": "/",
        "hostOnly": false,
        "creation": "2025-07-03T09:12:54.623Z",
        "lastAccessed": "2025-07-03T09:12:54.623Z"
    },
    {
        "key": "sb",
        "value": "wTdUaNBCAxW88j19hTBBkExo",
        "domain": "facebook.com",
        "path": "/",
        "hostOnly": false,
        "creation": "2025-07-03T09:12:54.623Z",
        "lastAccessed": "2025-07-03T09:12:54.623Z"
    },
    {
        "key": "pas",
        "value": "61573774132103%3AbjjDGOwGCj",
        "domain": "facebook.com",
        "path": "/",
        "hostOnly": false,
        "creation": "2025-07-03T09:12:54.623Z",
        "lastAccessed": "2025-07-03T09:12:54.623Z"
    },
    {
        "key": "ps_l",
        "value": "1",
        "domain": "facebook.com",
        "path": "/",
        "hostOnly": false,
        "creation": "2025-07-03T09:12:54.623Z",
        "lastAccessed": "2025-07-03T09:12:54.623Z"
    },
    {
        "key": "ps_n",
        "value": "1",
        "domain": "facebook.com",
        "path": "/",
        "hostOnly": false,
        "creation": "2025-07-03T09:12:54.623Z",
        "lastAccessed": "2025-07-03T09:12:54.623Z"
    },
    {
        "key": "dpr",
        "value": "2",
        "domain": "facebook.com",
        "path": "/",
        "hostOnly": false,
        "creation": "2025-07-03T09:12:54.623Z",
        "lastAccessed": "2025-07-03T09:12:54.623Z"
    },
    {
        "key": "vpd",
        "value": "v1%3B668x360x2",
        "domain": "facebook.com",
        "path": "/",
        "hostOnly": false,
        "creation": "2025-07-03T09:12:54.623Z",
        "lastAccessed": "2025-07-03T09:12:54.623Z"
    },
    {
        "key": "c_user",
        "value": "61573774132103",
        "domain": "facebook.com",
        "path": "/",
        "hostOnly": false,
        "creation": "2025-07-03T09:12:54.623Z",
        "lastAccessed": "2025-07-03T09:12:54.623Z"
    },
    {
        "key": "fr",
        "value": "0iy2KWl5C2pfgidxQ.AWfpB3hdjnpIhjkr-C3MvAuJKWRZjHAh46rp_cEDgjfvOAxsHS0.BoVDfB..AAA.0.0.BoZhin.AWfkAF8uEd0vfHli49Q7WxwDSfE",
        "domain": "facebook.com",
        "path": "/",
        "hostOnly": false,
        "creation": "2025-07-03T09:12:54.624Z",
        "lastAccessed": "2025-07-03T09:12:54.624Z"
    },
    {
        "key": "xs",
        "value": "16%3AvqBYO4lAAxO5WA%3A2%3A1751521447%3A-1%3A-1",
        "domain": "facebook.com",
        "path": "/",
        "hostOnly": false,
        "creation": "2025-07-03T09:12:54.624Z",
        "lastAccessed": "2025-07-03T09:12:54.624Z"
    },
    {
        "key": "locale",
        "value": "en_GB",
        "domain": "facebook.com",
        "path": "/",
        "hostOnly": false,
        "creation": "2025-07-03T09:12:54.624Z",
        "lastAccessed": "2025-07-03T09:12:54.624Z"
    },
    {
        "key": "fbl_st",
        "value": "101429213%3BT%3A29192232",
        "domain": "facebook.com",
        "path": "/",
        "hostOnly": false,
        "creation": "2025-07-03T09:12:54.624Z",
        "lastAccessed": "2025-07-03T09:12:54.624Z"
    },
    {
        "key": "wl_cbv",
        "value": "v2%3Bclient_version%3A2858%3Btimestamp%3A1751533969",
        "domain": "facebook.com",
        "path": "/",
        "hostOnly": false,
        "creation": "2025-07-03T09:12:54.624Z",
        "lastAccessed": "2025-07-03T09:12:54.624Z"
    }
        ]
